azure/cli/command_modules/__init__.py
azure_cli_command_modules_nspkg-2.0.2.dist-info/METADATA
azure_cli_command_modules_nspkg-2.0.2.dist-info/RECORD
azure_cli_command_modules_nspkg-2.0.2.dist-info/WHEEL
azure_cli_command_modules_nspkg-2.0.2.dist-info/top_level.txt
